slurmpilot/.DS_Store
slurmpilot/__init__.py
slurmpilot/callback/__init__.py
slurmpilot/callback/spinners.py
slurmpilot/cli.py
slurmpilot/config.py
slurmpilot/interface/jobs.py
slurmpilot/interface/jobs_adapted.py
slurmpilot/interface/live_progress.py
slurmpilot/interface/log.py
slurmpilot/interface/spinners.py
slurmpilot/interface/status.py
slurmpilot/interface/tryout.py
slurmpilot/jobpath.py
slurmpilot/remote_command.py
slurmpilot/slurm_wrapper.py
slurmpilot/util.py
slurmpilot-0.1.4.2.dist-info/METADATA
slurmpilot-0.1.4.2.dist-info/WHEEL
slurmpilot-0.1.4.2.dist-info/RECORD
