Metadata-Version: 2.1
Name: slurmpilot
Version: 0.1.4.2
Summary: A tool for launching and tracking Slurm jobs across many clusters in Python.
Home-page: https://github.com/geoalgo/slurmpilot
License: MIT
Keywords: ML ops,slurm,experiment management
Author: David Salinas
Author-email: check@mywebsite.com
Requires-Python: >=3.10.0
Classifier: License :: OSI Approved :: MIT License
Classifier: Programming Language :: Python :: 3
Classifier: Programming Language :: Python :: 3.10
Classifier: Programming Language :: Python :: 3.11
Classifier: Programming Language :: Python :: 3.12
Classifier: Programming Language :: Python :: 3.13
Classifier: Topic :: Scientific/Engineering
Requires-Dist: pandas (>=2.0)
Requires-Dist: paramiko (>=3.0)
Requires-Dist: pyyaml (>=5.0)
Project-URL: Repository, https://github.com/geoalgo/slurmpilot
